py_postgres/PyPostgres.py
py_postgres/QueryFactory.py
py_postgres/__init__.py
py_postgres-0.0.3.dist-info/LICENSE
py_postgres-0.0.3.dist-info/METADATA
py_postgres-0.0.3.dist-info/WHEEL
py_postgres-0.0.3.dist-info/top_level.txt
py_postgres-0.0.3.dist-info/RECORD
